sqlite_utils_sqlite_xsv/__init__.py
sqlite_utils_sqlite_xsv-0.2.1a13.dist-info/METADATA
sqlite_utils_sqlite_xsv-0.2.1a13.dist-info/WHEEL
sqlite_utils_sqlite_xsv-0.2.1a13.dist-info/entry_points.txt
sqlite_utils_sqlite_xsv-0.2.1a13.dist-info/top_level.txt
sqlite_utils_sqlite_xsv-0.2.1a13.dist-info/RECORD
