Metadata-Version: 2.1
Name: sqlite-utils-sqlite-xsv
Version: 0.2.1a13
Home-page: https://TODO.com
Author: TODO
License: MIT License, Apache License, Version 2.0
Requires-Dist: sqlite-utils
Requires-Dist: sqlite-xsv (==0.2.1-alpha.13)
